norwegian_numbers/__init__.py
norwegian_numbers/__main__.py
norwegian_numbers/util.py
norwegian_numbers-1.0.2.dist-info/LICENSE
norwegian_numbers-1.0.2.dist-info/METADATA
norwegian_numbers-1.0.2.dist-info/WHEEL
norwegian_numbers-1.0.2.dist-info/top_level.txt
norwegian_numbers-1.0.2.dist-info/RECORD
