Metadata-Version: 2.1
Name: norwegian-numbers
Version: 1.0.2
Summary: Make and verify official Norwegian numbers like: KID-nummer, organisasjonsnummer, fødselsnummer, kontonummer
Home-page: https://github.com/Ondkloss/norwegian-numbers
Author: Halvor Holsten Strand
Author-email: halvor.holsten.strand@gmail.com
License: MIT
Platform: UNKNOWN
